setup.py
unray/__init__.py
unray/gui.py
unray/unray_config.py
unray/envs/__init__.py
unray/envs/base_env.py
unray/envs/bridge_env.py
unray/envs/spaces.py
unray/envs/bridge/TCP_IP_Connector.py
unray/envs/bridge/__init__.py
unray-1.0.9.dist-info/LICENSE
unray-1.0.9.dist-info/METADATA
unray-1.0.9.dist-info/WHEEL
unray-1.0.9.dist-info/top_level.txt
unray-1.0.9.dist-info/RECORD
