Metadata-Version: 2.1
Name: unray
Version: 1.0.9
Summary: Framework for trainning Reinforcement Learning envs with RLlib and Unreal Eninge 5
Author-email: Valentina Hernández <vahernandezmo@unal.edu.co>, Andrés Morales <amoralesma@unal.edu.co>
Project-URL: Homepage, https://github.com/Nullspace-Colombia/unray-bridge/
Project-URL: Issues, https://github.com/Nullspace-Colombia/unray-bridge/issues
Classifier: Programming Language :: Python :: 3
Classifier: License :: OSI Approved :: MIT License
Classifier: Operating System :: OS Independent
Requires-Python: >=3.8
License-File: LICENSE
